whirlpool.cp35-win32.pyd
Whirlpool-1.0.0.data/data/whirlpool/Whirlpool.c
Whirlpool-1.0.0.data/data/whirlpool/nessie.h
Whirlpool-1.0.0.dist-info/DESCRIPTION.rst
Whirlpool-1.0.0.dist-info/METADATA
Whirlpool-1.0.0.dist-info/RECORD
Whirlpool-1.0.0.dist-info/WHEEL
Whirlpool-1.0.0.dist-info/metadata.json
Whirlpool-1.0.0.dist-info/top_level.txt
