Metadata-Version: 2.0
Name: Whirlpool
Version: 1.0.0
Summary: Whirlpool: Bindings for whirlpool hash reference implementation.
Home-page: https://github.com/oohlaf/python-whirlpool
Author: Olaf Conradi
Author-email: olaf@conradi.org
License: Public Domain
Download-URL: https://github.com/oohlaf/python-whirlpool/archive/1.0.0.zip
Keywords: digest hashlib whirlpool
Platform: any
Classifier: Development Status :: 5 - Production/Stable
Classifier: Intended Audience :: Developers
Classifier: License :: Public Domain
Classifier: Programming Language :: C
Classifier: Programming Language :: Python
Classifier: Programming Language :: Python :: 2
Classifier: Programming Language :: Python :: 2.7
Classifier: Programming Language :: Python :: 3
Classifier: Programming Language :: Python :: 3.3
Classifier: Programming Language :: Python :: 3.4
Classifier: Programming Language :: Python :: 3.5
Classifier: Programming Language :: Python :: 3.6
Classifier: Programming Language :: Python :: Implementation :: CPython
Classifier: Programming Language :: Python :: Implementation :: PyPy
Classifier: Topic :: Security :: Cryptography
Classifier: Topic :: Software Development :: Libraries :: Python Modules
Requires-Python: >=2.7,!=3.0.*,!=3.1.*,!=3.2.*
